deeptime-0.4.5.dist-info/RECORD
deeptime-0.4.5.dist-info/WHEEL
deeptime-0.4.5.dist-info/top_level.txt
deeptime-0.4.5.dist-info/METADATA
deeptime-0.4.5.dist-info/licenses/AUTHORS
deeptime-0.4.5.dist-info/licenses/LICENSE.txt
deeptime-0.4.5.data/data/CMakeLists.txt
deeptime-0.4.5.data/data/pyproject.toml
deeptime-0.4.5.data/data/LICENSE.txt
deeptime/base_torch.py
deeptime/_version.py
deeptime/__init__.py
deeptime/base.py
deeptime/kernels/_base.py
deeptime/kernels/__init__.py
deeptime/kernels/_kernels_torch.py
deeptime/kernels/_kernels.py
deeptime/util/matrix.py
deeptime/util/__init__.py
deeptime/util/types.py
deeptime/util/platform.py
deeptime/util/stats.py
deeptime/util/callbacks.py
deeptime/util/sparse.py
deeptime/util/exceptions.py
deeptime/util/diff.py
deeptime/util/parallel.py
deeptime/util/torch.py
deeptime/util/data.py
deeptime/util/validation.py
deeptime/util/decorators.py
deeptime/markov/_transition_matrix.py
deeptime/markov/_base.py
deeptime/markov/CMakeLists.txt
deeptime/markov/_discrete_states.py
deeptime/markov/__init__.py
deeptime/markov/_pcca.py
deeptime/markov/_girsanov_reweighted_transition_counting.py
deeptime/markov/_util.py
deeptime/markov/_transition_counting.py
deeptime/markov/_reactive_flux.py
deeptime/markov/_observables.py
deeptime/markov/_markov_bindings.cpython-313-darwin.so
deeptime/markov/tools/__init__.py
deeptime/markov/tools/analysis/_expectations.py
deeptime/markov/tools/analysis/_api.py
deeptime/markov/tools/analysis/_fingerprints.py
deeptime/markov/tools/analysis/__init__.py
deeptime/markov/tools/analysis/_decomposition.py
deeptime/markov/tools/analysis/_assessment.py
deeptime/markov/tools/analysis/_mean_first_passage_time.py
deeptime/markov/tools/analysis/_stationary_vector.py
deeptime/markov/tools/analysis/_committor.py
deeptime/markov/tools/analysis/dense/_hitting_probability.py
deeptime/markov/tools/analysis/dense/__init__.py
deeptime/markov/tools/analysis/dense/_sensitivity.py
deeptime/markov/tools/analysis/dense/_pcca.py
deeptime/markov/tools/analysis/dense/_correlations.py
deeptime/markov/tools/flux/__init__.py
deeptime/markov/tools/flux/pathways.py
deeptime/markov/tools/flux/api.py
