Metadata-Version: 2.4
Name: deeptime
Version: 0.4.5
Summary: Python library for analysis of time series data including dimensionality reduction, clustering, and Markov model estimation.
Author: Moritz Hoffmann, Martin Scherer, Tim Hempel, Andreas Mardt, Maaike Galama, Brian de Silva, Brooke Husic, Stefan Klus, Hao Wu, Nathan Kutz, Steven Brunton, Frank Noé
Project-URL: homepage, https://deeptime-ml.github.io
Project-URL: repository, https://github.com/deeptime-ml/deeptime
Project-URL: documentation, https://deeptime-ml.github.io
Project-URL: download, https://pypi.org/project/deeptime/#files
Keywords: markov-model,hidden-markov-model,time-series-analysis,covariance-estimation,koopman-operator,coherent-set-detection
Requires-Python: >=3.8
License-File: LICENSE.txt
License-File: AUTHORS
Requires-Dist: numpy
Requires-Dist: scipy>=1.9.0
Requires-Dist: scikit-learn>=1.5.0
Requires-Dist: threadpoolctl>=3.1.0
Provides-Extra: deep-learning
Requires-Dist: torch; extra == "deep-learning"
Provides-Extra: plotting
Requires-Dist: matplotlib; extra == "plotting"
Requires-Dist: networkx; extra == "plotting"
Provides-Extra: units
Requires-Dist: pint>=0.20; extra == "units"
Provides-Extra: tests
Requires-Dist: torch>=1.12.0; (platform_system != "Darwin" and platform_system != "Windows") and extra == "tests"
Requires-Dist: pytest>=7.1.2; extra == "tests"
Requires-Dist: pytest-cov>=3.0.0; extra == "tests"
Requires-Dist: coverage[toml]; extra == "tests"
Requires-Dist: pytest-xdist>=2.5.0; extra == "tests"
Requires-Dist: flaky>=3.7.0; extra == "tests"
Requires-Dist: tqdm>=4.64.0; extra == "tests"
Requires-Dist: cython>=0.29.30; extra == "tests"
Requires-Dist: pybind11>=2.10.1; extra == "tests"
Requires-Dist: networkx; extra == "tests"
Requires-Dist: matplotlib; extra == "tests"
Requires-Dist: cmake>=3.24; extra == "tests"
Requires-Dist: ninja; platform_system != "Windows" and extra == "tests"
Provides-Extra: docs
Requires-Dist: sphinx; extra == "docs"
Requires-Dist: nbsphinx; extra == "docs"
Requires-Dist: sphinxcontrib-bibtex; extra == "docs"
Requires-Dist: matplotlib; extra == "docs"
Requires-Dist: networkx; extra == "docs"
Requires-Dist: sphinxcontrib-katex; extra == "docs"
Requires-Dist: sphinx-gallery; extra == "docs"
Requires-Dist: torch; extra == "docs"
Requires-Dist: memory_profiler; extra == "docs"
Requires-Dist: mdshare; extra == "docs"
Requires-Dist: nbconvert; extra == "docs"
Requires-Dist: jupyter; extra == "docs"
Requires-Dist: tqdm; extra == "docs"
Dynamic: license-file
